orthoani/__init__.py
orthoani/__main__.py
orthoani/_main.py
pyorthoani/__init__.py
pyorthoani/__main__.py
pyorthoani/_main.py
pyorthoani/_utils.py
pyorthoani/py.typed
pyorthoani-0.7.0.dist-info/COPYING
pyorthoani-0.7.0.dist-info/METADATA
pyorthoani-0.7.0.dist-info/WHEEL
pyorthoani-0.7.0.dist-info/entry_points.txt
pyorthoani-0.7.0.dist-info/top_level.txt
pyorthoani-0.7.0.dist-info/RECORD
