Metadata-Version: 2.2
Name: pyorthoani
Version: 0.7.0
Summary: A Python implementation of the OrthoANI algorithm for nucleotide identity measurement.
Author-email: Martin Larralde <martin.larralde@embl.de>
License: MIT License
Project-URL: Bug Tracker, https://github.com/althonos/pyorthoani/issues
Project-URL: Changelog, https://github.com/althonos/pyorthoani/blob/master/CHANGELOG.md
Project-URL: CI, https://github.com/althonos/pyorthoani/actions
Keywords: ani,average,nucleotide,identity,genomic,taxonomy
Classifier: Development Status :: 4 - Beta
Classifier: Intended Audience :: Developers
Classifier: Intended Audience :: Science/Research
Classifier: License :: OSI Approved :: MIT License
Classifier: Operating System :: OS Independent
Classifier: Programming Language :: Python
Classifier: Programming Language :: Python :: 3
Classifier: Topic :: Software Development :: Libraries :: Python Modules
Classifier: Topic :: Scientific/Engineering :: Bio-Informatics
Classifier: Typing :: Typed
Requires-Python: >=3.6
License-File: COPYING
Requires-Dist: biopython~=1.73
Provides-Extra: cli
Requires-Dist: better-exceptions~=0.3.0; extra == "cli"
